httpx_defaults/__init__.py
httpx_defaults-1.0.0.dist-info/METADATA
httpx_defaults-1.0.0.dist-info/WHEEL
httpx_defaults-1.0.0.dist-info/RECORD
