Metadata-Version: 2.4
Name: httpx-defaults
Version: 1.0.0
Summary: Production-ready httpx client with secure defaults: timeouts, retries, connection limits.
Project-URL: Homepage, https://github.com/SerityOps/httpx-defaults
Project-URL: Documentation, https://github.com/SerityOps/httpx-defaults#readme
Project-URL: Repository, https://github.com/SerityOps/httpx-defaults
Project-URL: Issues, https://github.com/SerityOps/httpx-defaults/issues
Author: LadyCami
License: MIT
Keywords: client,defaults,http,httpx,production,requests,retry,secure,timeout
Classifier: Development Status :: 5 - Production/Stable
Classifier: Intended Audience :: Developers
Classifier: License :: OSI Approved :: MIT License
Classifier: Programming Language :: Python :: 3
Classifier: Programming Language :: Python :: 3.10
Classifier: Programming Language :: Python :: 3.11
Classifier: Programming Language :: Python :: 3.12
Classifier: Topic :: Internet :: WWW/HTTP
Classifier: Typing :: Typed
Requires-Python: >=3.10
Requires-Dist: httpx>=0.25.0
Provides-Extra: http2
Requires-Dist: h2>=4.0.0; extra == 'http2'
